foreca_api/__init__.py
foreca_api/api.py
foreca_api-0.1.1.dist-info/METADATA
foreca_api-0.1.1.dist-info/WHEEL
foreca_api-0.1.1.dist-info/top_level.txt
foreca_api-0.1.1.dist-info/zip-safe
foreca_api-0.1.1.dist-info/RECORD
