Metadata-Version: 2.1
Name: foreca-api
Version: 0.1.1
Summary: a package to integrate foreca weather api with python client
Home-page: https://github.com/AliBigdeli/Python-Foreca-Client
Author: Ali Bigdeli
Author-email: bigdeli.ali3@gmail.com
License: MIT
Keywords: Foreca,api,weather api,weather
Classifier: Development Status :: 5 - Production/Stable
Classifier: Intended Audience :: Developers
Classifier: License :: OSI Approved :: MIT License
Classifier: Environment :: Console
Classifier: Environment :: Web Environment
Classifier: Operating System :: Unix
Classifier: Operating System :: Microsoft :: Windows
Classifier: Programming Language :: Python
Classifier: Programming Language :: Python :: 3
Classifier: Programming Language :: Python :: 3.6
Classifier: Programming Language :: Python :: 3.7
Classifier: Programming Language :: Python :: 3.8
Classifier: Programming Language :: Python :: 3.9
Classifier: Programming Language :: Python :: 3.10
Requires-Dist: requests
